[{"author":"PUGET, Pierre","born-died":"(b. 1620, Marseille, d. 1694, Marseille)","title":"The Meeting of Alexander the Great and Diogenes","date":"1671-89","technique":"Marble, 332 x 296 cm","location":"Musée du Louvre, Paris","url":"https://www.wga.hu/html/p/puget/sculptur/2/12meetin.html","form":"sculpture","type":"historical","school":"French","timeline":"1651-1700"},{"author":"PUGET, Pierre","born-died":"(b. 1620, Marseille, d. 1694, Marseille)","title":"The Meeting of Alexander the Great and Diogenes","date":"1671-89","technique":"Marble, 332 x 296 cm","location":"Musée du Louvre, Paris","url":"https://www.wga.hu/html/p/puget/sculptur/2/12meetix.html","form":"sculpture","type":"historical","school":"French","timeline":"1651-1700"}]