[{"author":"BURNE-JONES, Edward","born-died":"(b. 1833, Birmingham, d. 1898, London)","title":"Garden of the Hesperides","date":"c. 1870","technique":"Watercolour and gouache on paper, 119 x 98 cm","location":"Kunsthalle, Hamburg","url":"https://www.wga.hu/html/b/burnejon/hesperid.html","form":"graphics","type":"mythological","school":"English","timeline":"1851-1900"},{"author":"BURNE-JONES, Edward","born-died":"(b. 1833, Birmingham, d. 1898, London)","title":"Well at the World's End","date":1896,"technique":"Woodcut","location":"Bodleian Library, Oxford","url":"https://www.wga.hu/html/b/burnejon/worldend.html","form":"graphics","type":"mythological","school":"English","timeline":"1851-1900"}]