[{"author":"BAERTSOEN, Albert","born-died":"(b. 1866, Gent, d. 1922, Gent)","title":"Ghent, Evening","date":1903,"technique":"Oil on canvas, 151 x 155 cm","location":"Musées Royaux des Beaux-Arts, Brussels","url":"https://www.wga.hu/html/b/baertsoe/evening.html","form":"painting","type":"landscape","school":"Belgian","timeline":"1851-1900"},{"author":"CLAUS, Emile","born-died":"(b. 1849, Sint-Eloois-Vijve, d. 1924, Astene)","title":"A Corner of My Garden","date":1901,"technique":"Oil on canvas, 60 x 74 cm","location":"Private collection","url":"https://www.wga.hu/html/c/claus/corner.html","form":"painting","type":"landscape","school":"Belgian","timeline":"1851-1900"},{"author":"CLAUS, Emile","born-died":"(b. 1849, Sint-Eloois-Vijve, d. 1924, Astene)","title":"Dew","date":"c. 1910","technique":"Oil on canvas, 132 x 140 cm","location":"Galleria Nazionale d'Arte Moderna e Contemporanea, Rome","url":"https://www.wga.hu/html/c/claus/dew.html","form":"painting","type":"landscape","school":"Belgian","timeline":"1851-1900"},{"author":"CLAUS, Emile","born-died":"(b. 1849, Sint-Eloois-Vijve, d. 1924, Astene)","title":"Sunshine","date":1899,"technique":"Oil on canvas, 81 x 117 cm","location":"Musée d'Orsay, Paris","url":"https://www.wga.hu/html/c/claus/sunshine.html","form":"painting","type":"landscape","school":"Belgian","timeline":"1851-1900"},{"author":"DEGOUVE DE NUNCQUES, William","born-died":"(b. 1867, Monthermé, d. 1935, Stavelot)","title":"The Blind House or The Pink House","date":1892,"technique":"Oil on canvas, 63 x 43 cm","location":"Rijksmuseum Kröller-Müller, Otterlo","url":"https://www.wga.hu/html/d/degouve/pinkhous.html","form":"painting","type":"landscape","school":"Belgian","timeline":"1851-1900"},{"author":"EVENEPOEL, Henri","born-died":"(b. 1872, Nice. d. 1899, Paris)","title":"Sunday in the Bois de Boulogne","date":1891,"technique":"Oil on canvas, 59 x 90 cm","location":"Koninklijk Museum voor Schone Kunsten, Antwerp","url":"https://www.wga.hu/html/e/evenepoe/sunday.html","form":"painting","type":"landscape","school":"Belgian","timeline":"1851-1900"},{"author":"FINCH, Alfred William","born-died":"(b. 1854, Bruxelles, d. 1930, Helsinki)","title":"Haystacks","date":1889,"technique":"Oil on canvas, 32 x 50 cm","location":"Musée d'Ixelles, Brussels","url":"https://www.wga.hu/html/f/finch/haystack.html","form":"painting","type":"landscape","school":"Belgian","timeline":"1851-1900"},{"author":"LEICKERT, Charles Henri Joseph","born-died":"(b. 1816, Bruxelles, d. 1907, Mainz)","title":"Skaters on a Frozen Pond","date":"-","technique":"Oil on panel, 28 x 38 cm","location":"Private collection","url":"https://www.wga.hu/html/l/leickert/skaters.html","form":"painting","type":"landscape","school":"Belgian","timeline":"1851-1900"},{"author":"LEICKERT, Charles Henri Joseph","born-died":"(b. 1816, Bruxelles, d. 1907, Mainz)","title":"Urban Landscape","date":1856,"technique":"Oil on canvas, 87 x 119 cm","location":"The Hermitage, St. Petersburg","url":"https://www.wga.hu/html/l/leickert/urban_la.html","form":"painting","type":"landscape","school":"Belgian","timeline":"1851-1900"},{"author":"LEMMEN, Georges","born-died":"(b. 1865, Schaerbeek, d. 1916, Ukkel)","title":"Beach at Heist","date":1891,"technique":"Oil on wood, 37 x 46 cm","location":"Musée d'Orsay, Paris","url":"https://www.wga.hu/html/l/lemmen/beach.html","form":"painting","type":"landscape","school":"Belgian","timeline":"1851-1900"},{"author":"LEMMEN, Georges","born-died":"(b. 1865, Schaerbeek, d. 1916, Ukkel)","title":"View of the Thames","date":1892,"technique":"Oil on canvas, 61 x 87 cm","location":"Museum of Art, Rhode Island School of Design, Providence","url":"https://www.wga.hu/html/l/lemmen/thames.html","form":"painting","type":"landscape","school":"Belgian","timeline":"1851-1900"},{"author":"RYSSELBERGHE, Théo van","born-died":"(b. 1862, Gent, d. 1926, Saint-Clair)","title":"Heavy Clouds, Christiania Fjord","date":1893,"technique":"Oil on canvas, 51 x 63 cm","location":"Museum of Art, Indianapolis","url":"https://www.wga.hu/html/r/rysselbe/clouds.html","form":"painting","type":"landscape","school":"Belgian","timeline":"1851-1900"},{"author":"RYSSELBERGHE, Théo van","born-died":"(b. 1862, Gent, d. 1926, Saint-Clair)","title":"The Man at the Helm","date":1892,"technique":"Oil on canvas, 60 x 80 cm","location":"Musée d'Orsay, Paris","url":"https://www.wga.hu/html/r/rysselbe/man_helm.html","form":"painting","type":"landscape","school":"Belgian","timeline":"1851-1900"},{"author":"RYSSELBERGHE, Théo van","born-died":"(b. 1862, Gent, d. 1926, Saint-Clair)","title":"Pointe Saint-Pierre at Saint-Tropez","date":1896,"technique":"Oil on canvas, 78 x 98 cm","location":"Musée National d'Histoire et d'Art, Luxembourg","url":"https://www.wga.hu/html/r/rysselbe/sttropez.html","form":"painting","type":"landscape","school":"Belgian","timeline":"1851-1900"},{"author":"VELDE, Henry van de","born-died":"(b. 1863, Antwerpen, d. 1957, Zürich)","title":"Bathing Huts at Blankenberge","date":1888,"technique":"Oil on canvas, 71 x 100 cm","location":"Kunsthaus, Zurich","url":"https://www.wga.hu/html/v/velde3/bathhuts.html","form":"painting","type":"landscape","school":"Belgian","timeline":"1851-1900"},{"author":"WILLEMS, Florent Joseph Marie","born-died":"(b. 1823. Liège, d. 1905, Neuilly-sur-Seine)","title":"A Sideways Glance","date":"-","technique":"Oil on panel, 74 x 58 cm","location":"Private collection","url":"https://www.wga.hu/html/w/willems/sideways.html","form":"painting","type":"landscape","school":"Belgian","timeline":"1851-1900"}]