[{"author":"FEUCHTMAYER, Joseph Anton","born-died":"(b. 1696, Wessobrun, d. 1770, Wessobrun)","title":"Honey-licking putto","date":"1746-53","technique":"Stucco","location":"Unsere Liebe Frau, Birnau","url":"https://www.wga.hu/html/f/feuchtma/joseph/angel.html","form":"sculpture","type":"other","school":"German","timeline":"1701-1750"},{"author":"PERMOSER, Balthasar","born-died":"(b. 1651, Kammer, d. 1732, Dresden)","title":"Supporting figures","date":"1700-10","technique":"Stone","location":"Zwinger, Dresden","url":"https://www.wga.hu/html/p/permoser/support.html","form":"sculpture","type":"other","school":"German","timeline":"1701-1750"}]