[{"author":"LEONARDO da Vinci","born-died":"(b. 1452, Vinci, d. 1519, Cloux, near Amboise)","title":"Landscape drawing for Santa Maria della Neve on 5th August 1473","date":1473,"technique":"Pen and ink, 190 x 285 mm","location":"Galleria degli Uffizi, Florence","url":"https://www.wga.hu/html/l/leonardo/11nature/01landsc.html","form":"graphics","type":"landscape","school":"Italian","timeline":"1451-1500"},{"author":"LEONARDO da Vinci","born-died":"(b. 1452, Vinci, d. 1519, Cloux, near Amboise)","title":"Cavern with ducks","date":"1482-85","technique":"Pen and ink on paper, 220 x 158 mm","location":"Royal Library, Windsor","url":"https://www.wga.hu/html/l/leonardo/11nature/02landsc.html","form":"graphics","type":"landscape","school":"Italian","timeline":"1451-1500"},{"author":"LEONARDO da Vinci","born-died":"(b. 1452, Vinci, d. 1519, Cloux, near Amboise)","title":"Storm over a landscape","date":"c. 1500","technique":"Red chalk on paper, 200 x 150 mm","location":"Royal Library, Windsor","url":"https://www.wga.hu/html/l/leonardo/11nature/03storm.html","form":"graphics","type":"landscape","school":"Italian","timeline":"1451-1500"},{"author":"LEONARDO da Vinci","born-died":"(b. 1452, Vinci, d. 1519, Cloux, near Amboise)","title":"Landscape near Pisa","date":"1502-03","technique":"Red chalk on paper, 211 x 150 mm","location":"Biblioteca Nacional, Madrid","url":"https://www.wga.hu/html/l/leonardo/11nature/04landsc.html","form":"graphics","type":"landscape","school":"Italian","timeline":"1451-1500"}]