[{"author":"BASSA, Arnau","born-died":"(active in second half of 14th century)","title":"The Consecration of St Marcus (detail)","date":"c. 1350","technique":"Panel","location":"Cathedral of Manresa, Barcelona","url":"https://www.wga.hu/html/b/bassa/arnaldo/marcus.html","form":"painting","type":"religious","school":"Catalan","timeline":"1351-1400"},{"author":"SERRA, Jaume","born-died":"(d. after 1405)","title":"The Last Supper","date":"1370-1400","technique":"Tempera on wood","location":"Museo Nazionale, Palermo","url":"https://www.wga.hu/html/s/serra/jaume/lastsupp.html","form":"painting","type":"religious","school":"Catalan","timeline":"1351-1400"},{"author":"SERRA, Pere","born-died":"(active 1363-1399)","title":"Madonna and Child with Angels Playing Music","date":"1390s","technique":"Tempera on wood, 196 x 130 cm","location":"Museu Nacional d'Art de Catalunya, Barcelona","url":"https://www.wga.hu/html/s/serra/pedro/mad_chil.html","form":"painting","type":"religious","school":"Catalan","timeline":"1351-1400"},{"author":"SERRA, Pere","born-died":"(active 1363-1399)","title":"Madonna with Angels Playing Music","date":"1390s","technique":"Panel, 196 x 130 cm","location":"Museu Nacional d'Art de Catalunya, Barcelona","url":"https://www.wga.hu/html/s/serra/pedro/madonna.html","form":"painting","type":"religious","school":"Catalan","timeline":"1351-1400"}]