[{"author":"BUYSTER, Philippe de","born-died":"(b. 1595, Antwerpen, d. 1688, Paris)","title":"De l'Aubespine Funerary Monument","date":"1656-58","technique":"Marble","location":"Cathédrale Saint Étienne, Bourges (Cher)","url":"https://www.wga.hu/html/b/buyster/aubespin.html","form":"sculpture","type":"religious","school":"Flemish","timeline":"1601-1650"},{"author":"CALSTER, Maarten van","born-died":"(b. ca. 1574, Mechelen, d. 1628, Mechelen)","title":"Virgin and Child","date":"C. 1600","technique":"Stone","location":"Magistrate's Hall, Mechelen","url":"https://www.wga.hu/html/c/calster/virgin_c.html","form":"sculpture","type":"religious","school":"Flemish","timeline":"1601-1650"},{"author":"DUQUESNOY, François","born-died":"(b. 1597, Bruxelles, d. 1643, Livorno)","title":"Epitaph of Ferdinand van den Eynde","date":1633,"technique":"Marble","location":"Santa Maria dell' Anima, Rome","url":"https://www.wga.hu/html/d/duquesno/francois/epitaph.html","form":"sculpture","type":"religious","school":"Flemish","timeline":"1601-1650"},{"author":"DUQUESNOY, François","born-died":"(b. 1597, Bruxelles, d. 1643, Livorno)","title":"St Andrew","date":"1629-33","technique":"Marble, height 450 cm","location":"Basilica di San Pietro, Vatican","url":"https://www.wga.hu/html/d/duquesno/francois/s_andrew.html","form":"sculpture","type":"religious","school":"Flemish","timeline":"1601-1650"},{"author":"DUQUESNOY, François","born-died":"(b. 1597, Bruxelles, d. 1643, Livorno)","title":"St Susanna","date":"1630-33","technique":"Marble","location":"Santa Maria di Loreto, Rome","url":"https://www.wga.hu/html/d/duquesno/francois/susanna.html","form":"sculpture","type":"religious","school":"Flemish","timeline":"1601-1650"},{"author":"DUQUESNOY, François","born-died":"(b. 1597, Bruxelles, d. 1643, Livorno)","title":"St Susanna (detail)","date":"1630-33","technique":"Marble","location":"Santa Maria di Loreto, Rome","url":"https://www.wga.hu/html/d/duquesno/francois/susanna1.html","form":"sculpture","type":"religious","school":"Flemish","timeline":"1601-1650"},{"author":"DUQUESNOY, Jérôme, the Elder","born-died":"(b. ca. 1570, Le Quesnoy, d. 1641, Brussel)","title":"Tabernacle","date":1604,"technique":"Marble","location":"Sint-Martinuskerk, Aalst","url":"https://www.wga.hu/html/d/duquesno/jerome1/tabernac.html","form":"sculpture","type":"religious","school":"Flemish","timeline":"1601-1650"},{"author":"DUQUESNOY, Jérôme, the Younger","born-died":"(b. 1602, Brussel, d. 1654, Brussel)","title":"Christ","date":"-","technique":"Ivory","location":"Church of the Beguinage, Mechelen","url":"https://www.wga.hu/html/d/duquesno/jerome2/christ.html","form":"sculpture","type":"religious","school":"Flemish","timeline":"1601-1650"},{"author":"DUQUESNOY, Jérôme, the Younger","born-died":"(b. 1602, Brussel, d. 1654, Brussel)","title":"St Thomas","date":1644,"technique":"Marble","location":"Sint-Michielskathedraal, Brussels","url":"https://www.wga.hu/html/d/duquesno/jerome2/thomas.html","form":"sculpture","type":"religious","school":"Flemish","timeline":"1601-1650"},{"author":"DUQUESNOY, Jérôme, the Younger","born-died":"(b. 1602, Brussel, d. 1654, Brussel)","title":"Tomb of Antonius Triest","date":1651,"technique":"Marble","location":"Cathedral of St Bavo, Ghent","url":"https://www.wga.hu/html/d/duquesno/jerome2/tomb1.html","form":"sculpture","type":"religious","school":"Flemish","timeline":"1601-1650"},{"author":"DUQUESNOY, Jérôme, the Younger","born-died":"(b. 1602, Brussel, d. 1654, Brussel)","title":"Tomb of Antonius Triest","date":1651,"technique":"Marble","location":"Cathedral of St Bavo, Ghent","url":"https://www.wga.hu/html/d/duquesno/jerome2/tomb2.html","form":"sculpture","type":"religious","school":"Flemish","timeline":"1601-1650"},{"author":"DUQUESNOY, Jérôme, the Younger","born-died":"(b. 1602, Brussel, d. 1654, Brussel)","title":"Tomb of Antonius Triest (detail)","date":1651,"technique":"Marble","location":"Cathedral of St Bavo, Ghent","url":"https://www.wga.hu/html/d/duquesno/jerome2/tomb3.html","form":"sculpture","type":"religious","school":"Flemish","timeline":"1601-1650"},{"author":"DUQUESNOY, Jérôme, the Younger","born-died":"(b. 1602, Brussel, d. 1654, Brussel)","title":"Tomb of Antonius Triest (detail)","date":1651,"technique":"Marble","location":"Cathedral of St Bavo, Ghent","url":"https://www.wga.hu/html/d/duquesno/jerome2/tomb4.html","form":"sculpture","type":"religious","school":"Flemish","timeline":"1601-1650"},{"author":"DUQUESNOY, Jérôme, the Younger","born-died":"(b. 1602, Brussel, d. 1654, Brussel)","title":"Tomb of Antonius Triest (detail)","date":1651,"technique":"Marble","location":"Cathedral of St Bavo, Ghent","url":"https://www.wga.hu/html/d/duquesno/jerome2/tomb5.html","form":"sculpture","type":"religious","school":"Flemish","timeline":"1601-1650"},{"author":"FAYDHERBE, Antoon","born-died":"(d. 1653, Mechelen)","title":"Our Lady of Seven Sorrows","date":1626,"technique":"Marble","location":"Onze-Lieve-Vrouw-over-de-Dijlekerk, Mechelen","url":"https://www.wga.hu/html/f/faydherb/antoon/7sorrows.html","form":"sculpture","type":"religious","school":"Flemish","timeline":"1601-1650"},{"author":"FAYDHERBE, Maria","born-died":"(b. 1587, Mechelen, d. 1643, Mechelen)","title":"Virgin and Child","date":"1640s","technique":"Marble, height 120 cm","location":"Sint-Pieters-en-Pauluskerk, Mechelen","url":"https://www.wga.hu/html/f/faydherb/maria/virgin_c.html","form":"sculpture","type":"religious","school":"Flemish","timeline":"1601-1650"},{"author":"LOO, Frans van","born-died":"(active 1607-1654 in Mechelen)","title":"St Andrew","date":"-","technique":"Boxwood, with glass inlay, height 16 cm","location":"Szépmûvészeti Múzeum, Budapest","url":"https://www.wga.hu/html/l/loo_f/standrew.html","form":"sculpture","type":"religious","school":"Flemish","timeline":"1601-1650"},{"author":"MILDERT, Johannes van","born-died":"(b. 1588, Königsberg, d. 1638, Antwerpen)","title":"Virgin Enthroned","date":"c. 1620","technique":"Stone","location":"Sint-Carolus-Borromeuskerk, Antwerp","url":"https://www.wga.hu/html/m/mildert/carolus.html","form":"sculpture","type":"religious","school":"Flemish","timeline":"1601-1650"},{"author":"MILDERT, Johannes van","born-died":"(b. 1588, Königsberg, d. 1638, Antwerpen)","title":"St Simon Zelotes","date":1638,"technique":"Stone","location":"Sint-Romboutskathedraal, Mechelen","url":"https://www.wga.hu/html/m/mildert/rombout1.html","form":"sculpture","type":"religious","school":"Flemish","timeline":"1601-1650"},{"author":"MILDERT, Johannes van","born-died":"(b. 1588, Königsberg, d. 1638, Antwerpen)","title":"St John","date":"1631-37","technique":"Marble","location":"Sint-Romboutskathedraal, Mechelen","url":"https://www.wga.hu/html/m/mildert/rombout2.html","form":"sculpture","type":"religious","school":"Flemish","timeline":"1601-1650"},{"author":"NOLE, Andries de","born-died":"(b. 1598, Antwerpen, d. 1638, Antwerpen)","title":"St Andrew","date":"1631-37","technique":"Marble","location":"Sint-Romboutskathedraal, Mechelen","url":"https://www.wga.hu/html/n/nole/andries/andrew1.html","form":"sculpture","type":"religious","school":"Flemish","timeline":"1601-1650"},{"author":"NOLE, Andries de","born-died":"(b. 1598, Antwerpen, d. 1638, Antwerpen)","title":"St Andrew","date":"1631-37","technique":"Marble","location":"Sint-Romboutskathedraal, Mechelen","url":"https://www.wga.hu/html/n/nole/andries/andrew2.html","form":"sculpture","type":"religious","school":"Flemish","timeline":"1601-1650"},{"author":"NOLE, Andries de","born-died":"(b. 1598, Antwerpen, d. 1638, Antwerpen)","title":"St Andrew (detail)","date":"1631-37","technique":"Marble","location":"Sint-Romboutskathedraal, Mechelen","url":"https://www.wga.hu/html/n/nole/andries/andrew3.html","form":"sculpture","type":"religious","school":"Flemish","timeline":"1601-1650"},{"author":"NOLE, Robert de","born-died":"(b. ca. 1570, Utrecht, d. 1636, Antwerpen)","title":"High Altar","date":1622,"technique":"Marble","location":"Onze-Lieve-Vrouwekerk, Scherpenheuvel","url":"https://www.wga.hu/html/n/nole/robert/altar.html","form":"sculpture","type":"religious","school":"Flemish","timeline":"1601-1650"},{"author":"NOLE, Robert de","born-died":"(b. ca. 1570, Utrecht, d. 1636, Antwerpen)","title":"St Thomas","date":"1631-37","technique":"Marble","location":"Sint-Romboutskathedraal, Mechelen","url":"https://www.wga.hu/html/n/nole/robert/rombout1.html","form":"sculpture","type":"religious","school":"Flemish","timeline":"1601-1650"},{"author":"NOLE, Robert de","born-died":"(b. ca. 1570, Utrecht, d. 1636, Antwerpen)","title":"St Peter (detail)","date":"1631-37","technique":"Marble","location":"Sint-Romboutskathedraal, Mechelen","url":"https://www.wga.hu/html/n/nole/robert/rombout2.html","form":"sculpture","type":"religious","school":"Flemish","timeline":"1601-1650"},{"author":"NOLE, Robert de","born-died":"(b. ca. 1570, Utrecht, d. 1636, Antwerpen)","title":"St Philip","date":"1631-37","technique":"Marble","location":"Sint-Romboutskathedraal, Mechelen","url":"https://www.wga.hu/html/n/nole/robert/rombout3.html","form":"sculpture","type":"religious","school":"Flemish","timeline":"1601-1650"},{"author":"NOLE, Robert de","born-died":"(b. ca. 1570, Utrecht, d. 1636, Antwerpen)","title":"St James the Greater","date":"1631-37","technique":"Marble","location":"Sint-Romboutskathedraal, Mechelen","url":"https://www.wga.hu/html/n/nole/robert/rombout4.html","form":"sculpture","type":"religious","school":"Flemish","timeline":"1601-1650"},{"author":"QUELLINUS, Artus I","born-died":"(b. 1609, Antwerpen, d. 1668, Antwerpen)","title":"Madonna Ara Coeli","date":"c. 1644","technique":"Marble","location":"Sint-Michielskathedraal, Brussels","url":"https://www.wga.hu/html/q/quellin/artus/aracoeli.html","form":"sculpture","type":"religious","school":"Flemish","timeline":"1601-1650"},{"author":"QUELLINUS, Artus I","born-died":"(b. 1609, Antwerpen, d. 1668, Antwerpen)","title":"Mater Dolorosa","date":1650,"technique":"Polychrome wood","location":"Sint-Jacobskerk, Antwerp","url":"https://www.wga.hu/html/q/quellin/artus/dolorosa.html","form":"sculpture","type":"religious","school":"Flemish","timeline":"1601-1650"},{"author":"QUELLINUS, Artus I","born-died":"(b. 1609, Antwerpen, d. 1668, Antwerpen)","title":"Pietà","date":"1660s","technique":"Polychromed wood, height 147 cm","location":"O.-L. Vrouwekathedraal, Antwerp","url":"https://www.wga.hu/html/q/quellin/artus/pieta.html","form":"sculpture","type":"religious","school":"Flemish","timeline":"1601-1650"},{"author":"QUELLINUS, Artus I","born-died":"(b. 1609, Antwerpen, d. 1668, Antwerpen)","title":"Choir Stalls","date":"-","technique":"Wood","location":"Sint-Jacobskerk, Antwerp","url":"https://www.wga.hu/html/q/quellin/artus/stalls.html","form":"sculpture","type":"religious","school":"Flemish","timeline":"1601-1650"},{"author":"QUELLINUS, Artus I","born-died":"(b. 1609, Antwerpen, d. 1668, Antwerpen)","title":"St Peter","date":"c. 1658","technique":"Terracotta, height 90 cm","location":"Musées Royaux des Beaux-Arts, Brussels","url":"https://www.wga.hu/html/q/quellin/artus/stpeter.html","form":"sculpture","type":"religious","school":"Flemish","timeline":"1601-1650"}]