[{"author":"AMENDOLA, Giovanni Battista","born-died":"(b. 1848, Episcopio di Sarno, d. 1887, Napoli)","title":"Venus","date":"-","technique":"Bronze, golden brown and dark brown patina, height 87 cm","location":"Private collection","url":"https://www.wga.hu/html/a/amendola/venus.html","form":"sculpture","type":"mythological","school":"Italian","timeline":"1851-1900"},{"author":"CARADOSSI, Vittorio","born-died":"(b. 1861, Firenze, d. 1918, Firenze)","title":"Shooting Stars","date":"-","technique":"Carrara marble, height 154 cm","location":"Private collection","url":"https://www.wga.hu/html/c/carados/shooting.html","form":"sculpture","type":"mythological","school":"Italian","timeline":"1851-1900"},{"author":"D'ORSI, Achille","born-died":"(b. 1845, Napoli, d. 1929, Napoli)","title":"Proximus Tuus","date":"-","technique":"Bronze, dark brown patina, 35 x 44 cm","location":"Private collection","url":"https://www.wga.hu/html/d/d_orsi/proximux.html","form":"sculpture","type":"mythological","school":"Italian","timeline":"1851-1900"}]