[{"author":"BEEST, Sybrand van","born-died":"(b. ca. 1610, Den Haag, d. 1674, Amsterdam)","title":"'Vrouwe Wereld': Allegory of Transience","date":"-","technique":"Oil on panel, 42 x 71 cm","location":"Private collection","url":"https://www.wga.hu/html/b/beest/allegory.html","form":"painting","type":"mythological","school":"Dutch","timeline":"1651-1700"},{"author":"BERCHEM, Nicolaes","born-died":"(b. 1620, Haarlem, d. 1683, Amsterdam)","title":"Jupiter Notices Callisto","date":1656,"technique":"Oil on canvas, 129 x 168 cm","location":"Private collection","url":"https://www.wga.hu/html/b/berchem/jupiter.html","form":"painting","type":"mythological","school":"Dutch","timeline":"1651-1700"},{"author":"BLOMMENDAEL, Reyer van","born-died":"(b. 1628, Amsterdam, d. 1675, Haarlem)","title":"Paris and Oenone","date":"c. 1655","technique":"Oil on canvas, 123 x 110 cm","location":"Palais des Beaux-Arts, Lille","url":"https://www.wga.hu/html/b/blommend/parisoen.html","form":"painting","type":"mythological","school":"Dutch","timeline":"1651-1700"},{"author":"BLOMMENDAEL, Reyer van","born-died":"(b. 1628, Amsterdam, d. 1675, Haarlem)","title":"Xantippe Dousing Socrates","date":"c. 1655","technique":"Oil on canvas, 210 x 198 cm","location":"Musée des Beaux-Arts, Strasbourg","url":"https://www.wga.hu/html/b/blommend/xantippe.html","form":"painting","type":"mythological","school":"Dutch","timeline":"1651-1700"},{"author":"BOL, Ferdinand","born-died":"(b. 1616, Dordrecht, d. 1680, Amsterdam)","title":"Bacchus and Ariadne","date":1664,"technique":"Oil on canvas, 161 x 183 cm","location":"The Hermitage, St. Petersburg","url":"https://www.wga.hu/html/b/bol/bacchus.html","form":"painting","type":"mythological","school":"Dutch","timeline":"1651-1700"},{"author":"BOL, Ferdinand","born-died":"(b. 1616, Dordrecht, d. 1680, Amsterdam)","title":"Shepherdess in a Landscape","date":"-","technique":"Oil on canvas, 96 x 86 cm","location":"Private collection","url":"https://www.wga.hu/html/b/bol/shepherd.html","form":"painting","type":"mythological","school":"Dutch","timeline":"1651-1700"},{"author":"BOL, Ferdinand","born-died":"(b. 1616, Dordrecht, d. 1680, Amsterdam)","title":"Venus and Adonis","date":"c. 1658","technique":"Oil on canvas, 168 x 230 cm","location":"Rijksmuseum, Amsterdam","url":"https://www.wga.hu/html/b/bol/venus_ad.html","form":"painting","type":"mythological","school":"Dutch","timeline":"1651-1700"},{"author":"BRAY, Jan de","born-died":"(b. ca. 1627, Haarlem, d. 1697, Haarlem)","title":"Bacchus","date":"c. 1665","technique":"Oil on panel, 23 x 18 cm","location":"Private collection","url":"https://www.wga.hu/html/b/bray/jan/bacchus.html","form":"painting","type":"mythological","school":"Dutch","timeline":"1651-1700"},{"author":"BRAY, Jan de","born-died":"(b. ca. 1627, Haarlem, d. 1697, Haarlem)","title":"The Discovery of Achilles among the Daughters of Lycomedes","date":1664,"technique":"Oil on canvas, 129 x 179 cm","location":"Muzeum Narodowe, Warsaw","url":"https://www.wga.hu/html/b/bray/jan/lycomede.html","form":"painting","type":"mythological","school":"Dutch","timeline":"1651-1700"},{"author":"DUJARDIN, Karel","born-died":"(b. 1622, Amsterdam, d. 1678, Venezia)","title":"The Battle of Centaurs and Lapiths at Hippodamia's Wedding","date":1667,"technique":"Oil on canvas, 177 x 139 cm","location":"Schloss Sanssouci, Potsdam","url":"https://www.wga.hu/html/d/dujardin/4battle.html","form":"painting","type":"mythological","school":"Dutch","timeline":"1651-1700"},{"author":"DUJARDIN, Karel","born-died":"(b. 1622, Amsterdam, d. 1678, Venezia)","title":"Allegory","date":1663,"technique":"Oil on canvas, 116 x 97 cm","location":"Statens Museum for Kunst, Copenhagen","url":"https://www.wga.hu/html/d/dujardin/allegory.html","form":"painting","type":"mythological","school":"Dutch","timeline":"1651-1700"},{"author":"DUJARDIN, Karel","born-died":"(b. 1622, Amsterdam, d. 1678, Venezia)","title":"Pallas Athene Visits Invidia","date":1652,"technique":"Oil on wood, 27 x 21 cm","location":"Akademie der bildenden Künste, Vienna","url":"https://www.wga.hu/html/d/dujardin/pallas_a.html","form":"painting","type":"mythological","school":"Dutch","timeline":"1651-1700"},{"author":"EECKHOUT, Gerbrand van den","born-died":"(b. 1621, Amsterdam, d. 1674, Amsterdam)","title":"Vertumnus and Pomona","date":1669,"technique":"Oil on canvas, 127,5 x 103,5 cm","location":"Szépmûvészeti Múzeum, Budapest","url":"https://www.wga.hu/html/e/eeckhout/vertumnu.html","form":"painting","type":"mythological","school":"Dutch","timeline":"1651-1700"},{"author":"EVERDINGEN, Caesar van","born-died":"(b. 1617, Alkmaar, d. 1678, Alkmaar)","title":"Allegory of the Birth of Frederik Hendrik","date":"c. 1650","technique":"Oil on canvas, 373 x 243 cm","location":"Huis ten Bosch, The Hague","url":"https://www.wga.hu/html/e/everding/caesar/1birth_f.html","form":"painting","type":"mythological","school":"Dutch","timeline":"1651-1700"},{"author":"EVERDINGEN, Caesar van","born-died":"(b. 1617, Alkmaar, d. 1678, Alkmaar)","title":"Four Muses and Pegasus on Parnassus","date":"c. 1650","technique":"Oil on canvas, 340 x 230 cm","location":"Huis ten Bosch, The Hague","url":"https://www.wga.hu/html/e/everding/caesar/2fourmus.html","form":"painting","type":"mythological","school":"Dutch","timeline":"1651-1700"},{"author":"EVERDINGEN, Caesar van","born-died":"(b. 1617, Alkmaar, d. 1678, Alkmaar)","title":"Amor Holding a Glass Orb","date":"c. 1660","technique":"Oil on canvas, 89 x 102 cm","location":"Private collection","url":"https://www.wga.hu/html/e/everding/caesar/amor_orb.html","form":"painting","type":"mythological","school":"Dutch","timeline":"1651-1700"},{"author":"EVERDINGEN, Caesar van","born-died":"(b. 1617, Alkmaar, d. 1678, Alkmaar)","title":"Bacchus with Nymphs and Cupid","date":"c. 1660","technique":"Oil on canvas, 147 x 161 cm","location":"Gemäldegalerie, Dresden","url":"https://www.wga.hu/html/e/everding/caesar/bacchus.html","form":"painting","type":"mythological","school":"Dutch","timeline":"1651-1700"},{"author":"EVERDINGEN, Caesar van","born-died":"(b. 1617, Alkmaar, d. 1678, Alkmaar)","title":"Diogenes Seeks a True Man","date":1652,"technique":"Oil on canvas on panel, 76 x 104 cm","location":"Mauritshuis, The Hague","url":"https://www.wga.hu/html/e/everding/caesar/diogenes.html","form":"painting","type":"mythological","school":"Dutch","timeline":"1651-1700"},{"author":"EVERDINGEN, Caesar van","born-died":"(b. 1617, Alkmaar, d. 1678, Alkmaar)","title":"Jupiter and Callisto","date":1655,"technique":"Oil on canvas, 165 x 193 cm","location":"Nationalmuseum, Stockholm","url":"https://www.wga.hu/html/e/everding/caesar/jupiter.html","form":"painting","type":"mythological","school":"Dutch","timeline":"1651-1700"},{"author":"EVERDINGEN, Caesar van","born-died":"(b. 1617, Alkmaar, d. 1678, Alkmaar)","title":"Lycurgus Demonstrates the Benefits of Education","date":"1660-62","technique":"Oil on canvas, 167 x 219 cm","location":"Stedelijk Museum, Alkmaar","url":"https://www.wga.hu/html/e/everding/caesar/lycurgus.html","form":"painting","type":"mythological","school":"Dutch","timeline":"1651-1700"},{"author":"EVERDINGEN, Caesar van","born-died":"(b. 1617, Alkmaar, d. 1678, Alkmaar)","title":"Nymphs Offering the Young Bacchus Wine, Fruit and Flowers","date":"1670-78","technique":"Oil on canvas, 162 x 180 cm","location":"Museum Kunstpalast, Düsseldorf","url":"https://www.wga.hu/html/e/everding/caesar/nymphs.html","form":"painting","type":"mythological","school":"Dutch","timeline":"1651-1700"},{"author":"EVERSDIJCK, Willem","born-died":"(b. ca. 1616, Goes, d. 1671, Middelburg)","title":"Allegory of the Flowering of the Dutch Fishery","date":"-","technique":"Oil on canvas, 114 x 162 cm","location":"Rijksmuseum, Amsterdam","url":"https://www.wga.hu/html/e/eversdij/allegory.html","form":"painting","type":"mythological","school":"Dutch","timeline":"1651-1700"},{"author":"FABRITIUS, Barent","born-died":"(b. 1624, Midden-Beemster, d. 1673, Amsterdam)","title":"Ruth and Boaz","date":1660,"technique":"Oil on panel, 49 x 39 cm","location":"The Hermitage, St. Petersburg","url":"https://www.wga.hu/html/f/fabritiu/barent/ruthboaz.html","form":"painting","type":"mythological","school":"Dutch","timeline":"1651-1700"},{"author":"HAENSBERGEN, Johan van","born-died":"(b. 1642, Gorinchem, d. 1705, Den Haag)","title":"A Bacchanal in an Extensive Landscape","date":"-","technique":"Oil on canvas, 43 x 50 cm","location":"Private collection","url":"https://www.wga.hu/html/h/haensber/bacchana.html","form":"painting","type":"mythological","school":"Dutch","timeline":"1651-1700"},{"author":"HOET, Gerard I","born-died":"(b. 1648, Zaltbommel, d. 1733, Den Haag)","title":"Diana and Callisto","date":"c. 1710","technique":"Oil on copper, 35 x 45 cm","location":"Private collection","url":"https://www.wga.hu/html/h/hoet/dianacal.html","form":"painting","type":"mythological","school":"Dutch","timeline":"1651-1700"},{"author":"HOET, Gerard I","born-died":"(b. 1648, Zaltbommel, d. 1733, Den Haag)","title":"The Head of Cyrus being Presented to Queen Tomyris","date":"-","technique":"Oil on canvas, 54 x 64 cm","location":"Private collection","url":"https://www.wga.hu/html/h/hoet/tomyris.html","form":"painting","type":"mythological","school":"Dutch","timeline":"1651-1700"},{"author":"HOET, Gerard I","born-died":"(b. 1648, Zaltbommel, d. 1733, Den Haag)","title":"Vertumnus and Pomona","date":"1700s","technique":"Oil on canvas, 65 x 54 cm","location":"The Hermitage, St. Petersburg","url":"https://www.wga.hu/html/h/hoet/vertumnu.html","form":"painting","type":"mythological","school":"Dutch","timeline":"1651-1700"},{"author":"HONDIUS, Abraham Danielsz.","born-died":"(b. ca. 1625, Rotterdam, d. 1691, London)","title":"Mercury and Argos","date":"-","technique":"Oil on canvas, 99 x 126 cm","location":"Private collection","url":"https://www.wga.hu/html/h/hondius/mercury.html","form":"painting","type":"mythological","school":"Dutch","timeline":"1651-1700"},{"author":"HOUBRAKEN, Arnold","born-died":"(b. 1660, Dordrecht, d. 1719, Amsterdam)","title":"Pallas Athene Visiting Apollo on the Parnassus","date":1703,"technique":"Oil on canvas, 71 x 96 cm","location":"Dordrechts Museum, Dordrecht","url":"https://www.wga.hu/html/h/houbrake/pallas_a.html","form":"painting","type":"mythological","school":"Dutch","timeline":"1651-1700"},{"author":"LAIRESSE, Gérard de","born-died":"(b. 1641, Liège, d. 1711, The Hague)","title":"Allegory of the Five Senses","date":1668,"technique":"Oil on canvas","location":"Glasgow Museum, Glasgow","url":"https://www.wga.hu/html/l/lairesse/5senses.html","form":"painting","type":"mythological","school":"Dutch","timeline":"1651-1700"},{"author":"LAIRESSE, Gérard de","born-died":"(b. 1641, Liège, d. 1711, The Hague)","title":"Allegory of the Freedom of Trade","date":1672,"technique":"Ceiling painting","location":"Peace Palace, The Hague","url":"https://www.wga.hu/html/l/lairesse/allegory.html","form":"painting","type":"mythological","school":"Dutch","timeline":"1651-1700"},{"author":"LAIRESSE, Gérard de","born-died":"(b. 1641, Liège, d. 1711, The Hague)","title":"Allegory of Wisdom Fostering the Arts and Sciences","date":1670,"technique":"Oil on canvas, 65 x 78 cm","location":"Private collection","url":"https://www.wga.hu/html/l/lairesse/allegwis.html","form":"painting","type":"mythological","school":"Dutch","timeline":"1651-1700"},{"author":"LAIRESSE, Gérard de","born-died":"(b. 1641, Liège, d. 1711, The Hague)","title":"Apollo and Aurora","date":1671,"technique":"Oil on canvas, 205 x 193 cm","location":"Metropolitan Museum of Art, New York","url":"https://www.wga.hu/html/l/lairesse/aurora.html","form":"painting","type":"mythological","school":"Dutch","timeline":"1651-1700"},{"author":"LAIRESSE, Gérard de","born-died":"(b. 1641, Liège, d. 1711, The Hague)","title":"Apollo and Aurora","date":1671,"technique":"Oil on canvas, 205 x 193 cm","location":"Metropolitan Museum of Art, New York","url":"https://www.wga.hu/html/l/lairesse/aurora1.html","form":"painting","type":"mythological","school":"Dutch","timeline":"1651-1700"},{"author":"LAIRESSE, Gérard de","born-died":"(b. 1641, Liège, d. 1711, The Hague)","title":"Apollo and Aurora (detail)","date":1671,"technique":"Oil on canvas","location":"Metropolitan Museum of Art, New York","url":"https://www.wga.hu/html/l/lairesse/aurora2.html","form":"painting","type":"mythological","school":"Dutch","timeline":"1651-1700"},{"author":"LAIRESSE, Gérard de","born-died":"(b. 1641, Liège, d. 1711, The Hague)","title":"Diana and Endymion","date":"c. 1680","technique":"Oil on canvas, 177 x 119 cm","location":"Rijksmuseum, Amsterdam","url":"https://www.wga.hu/html/l/lairesse/diana_en.html","form":"painting","type":"mythological","school":"Dutch","timeline":"1651-1700"},{"author":"LAIRESSE, Gérard de","born-died":"(b. 1641, Liège, d. 1711, The Hague)","title":"Achilles Discovered among the Daughters of Lycomedes","date":"c. 1685","technique":"Oil on canvas, 138 x 190 cm","location":"Mauritshuis, The Hague","url":"https://www.wga.hu/html/l/lairesse/lycomed1.html","form":"painting","type":"mythological","school":"Dutch","timeline":"1651-1700"},{"author":"LAIRESSE, Gérard de","born-died":"(b. 1641, Liège, d. 1711, The Hague)","title":"Achilles Discovered among the Daughters of Lycomedes","date":"c. 1685","technique":"Oil on canvas, 150 x 181 cm","location":"Nationalmuseum, Stockholm","url":"https://www.wga.hu/html/l/lairesse/lycomed2.html","form":"painting","type":"mythological","school":"Dutch","timeline":"1651-1700"},{"author":"LAIRESSE, Gérard de","born-died":"(b. 1641, Liège, d. 1711, The Hague)","title":"Odysseus and Calypso","date":"-","technique":"Oil on canvas, 125 x 94 cm","location":"Rijksmuseum, Amsterdam","url":"https://www.wga.hu/html/l/lairesse/odysseus.html","form":"painting","type":"mythological","school":"Dutch","timeline":"1651-1700"},{"author":"LAIRESSE, Gérard de","born-died":"(b. 1641, Liège, d. 1711, The Hague)","title":"Venus Presenting Weapons to Aeneas","date":"-","technique":"Oil on canvas, 161,8 x 165,8 cm","location":"Museum Mayer van den Bergh, Antwerp","url":"https://www.wga.hu/html/l/lairesse/venus_ae.html","form":"painting","type":"mythological","school":"Dutch","timeline":"1651-1700"},{"author":"LOO, Jacob van","born-died":"(b. 1614, Sluis, d. 1670, Paris)","title":"Diana and Her Nymphs","date":1654,"technique":"Oil on canvas, 100 x 136 cm","location":"Statens Museum for Kunst, Copenhagen","url":"https://www.wga.hu/html/l/loo/jacob/diana_ny.html","form":"painting","type":"mythological","school":"Dutch","timeline":"1651-1700"},{"author":"MIERIS, Frans van, the Elder","born-died":"(b. 1635, Leiden, d. 1681, Leiden)","title":"Pictura (An Allegory of Painting)","date":1661,"technique":"Oil on copper","location":"Private collection","url":"https://www.wga.hu/html/m/mieris/frans/pictura.html","form":"painting","type":"mythological","school":"Dutch","timeline":"1651-1700"},{"author":"MIJTENS, Daniel II","born-died":"(b. 1644, Den Haag, d. 1688, Den Haag)","title":"Danaë","date":"-","technique":"Oil on canvas, 184 x 143 cm","location":"Private collection","url":"https://www.wga.hu/html/m/mijtens/daniel2/danae.html","form":"painting","type":"mythological","school":"Dutch","timeline":"1651-1700"},{"author":"NEER, Eglon van der","born-died":"(b. 1634, Amsterdam, d. 1703, Düsseldorf)","title":"Allegory of Religion","date":1693,"technique":"Oil on panel, 26 x 20 cm","location":"Amstelkring Museum, Amsterdam","url":"https://www.wga.hu/html/n/neer/eglon/religion.html","form":"painting","type":"mythological","school":"Dutch","timeline":"1651-1700"},{"author":"OSTADE, Adriaen Jansz. van","born-died":"(b. 1610, Haarlem, d. 1685, Haarlem)","title":"A Man With Pince-Nez (The Sense of Sight)","date":"-","technique":"Oil on panel, 16 x 11 cm","location":"Private collection","url":"https://www.wga.hu/html/o/ostade/adriaen/2/pincene.html","form":"painting","type":"mythological","school":"Dutch","timeline":"1651-1700"},{"author":"SCHALCKEN, Godfried","born-died":"(b. 1643, Made, d. 1706, Den Haag)","title":"Cephalus and Procris","date":"1680s","technique":"Oil on canvas, 65 x 80 cm","location":"Metropolitan Museum of Art, New York","url":"https://www.wga.hu/html/s/schalcke/cephalus.html","form":"painting","type":"mythological","school":"Dutch","timeline":"1651-1700"},{"author":"STEEN, Jan","born-died":"(b. 1626, Leiden, d. 1679, Leiden)","title":"The Scholar and Death","date":"1660s","technique":"Oil on oak panel, 47 x 43 cm","location":"Národní Galerie, Prague","url":"https://www.wga.hu/html/s/steen/page2/scholar.html","form":"painting","type":"mythological","school":"Dutch","timeline":"1651-1700"},{"author":"TOORENVLIET, Jacob","born-died":"(b. 1640, Leiden, d. 1719, Oegstgeest)","title":"Allegory of the Arts","date":"-","technique":"Oil on oak panel, 39 x 29 cm","location":"Private collection","url":"https://www.wga.hu/html/t/toorenvl/allegor.html","form":"painting","type":"mythological","school":"Dutch","timeline":"1651-1700"},{"author":"TOORENVLIET, Jacob","born-died":"(b. 1640, Leiden, d. 1719, Oegstgeest)","title":"An Allegory on Harmony","date":1684,"technique":"Oil on canvas, 46 x 38 cm","location":"Private collection","url":"https://www.wga.hu/html/t/toorenvl/allegory.html","form":"painting","type":"mythological","school":"Dutch","timeline":"1651-1700"},{"author":"VERMEER, Johannes","born-died":"(b. 1632, Delft, d. 1675, Delft)","title":"Diana and her Companions","date":"1655-56","technique":"Oil on canvas, 98,5 x 105 cm","location":"Mauritshuis, The Hague","url":"https://www.wga.hu/html/v/vermeer/01-early/03diana.html","form":"painting","type":"mythological","school":"Dutch","timeline":"1651-1700"},{"author":"VERMEER, Johannes","born-died":"(b. 1632, Delft, d. 1675, Delft)","title":"The Art of Painting","date":"1665-67","technique":"Oil on canvas, 120 x 100 cm","location":"Kunsthistorisches Museum, Vienna","url":"https://www.wga.hu/html/v/vermeer/03c/25artpa.html","form":"painting","type":"mythological","school":"Dutch","timeline":"1651-1700"},{"author":"VERMEER, Johannes","born-died":"(b. 1632, Delft, d. 1675, Delft)","title":"The Art of Painting (detail)","date":"1665-67","technique":"Oil on canvas","location":"Kunsthistorisches Museum, Vienna","url":"https://www.wga.hu/html/v/vermeer/03c/25artpa1.html","form":"painting","type":"mythological","school":"Dutch","timeline":"1651-1700"},{"author":"VERMEER, Johannes","born-died":"(b. 1632, Delft, d. 1675, Delft)","title":"The Art of Painting (detail)","date":"1665-67","technique":"Oil on canvas","location":"Kunsthistorisches Museum, Vienna","url":"https://www.wga.hu/html/v/vermeer/03c/25artpa2.html","form":"painting","type":"mythological","school":"Dutch","timeline":"1651-1700"},{"author":"VERMEER, Johannes","born-died":"(b. 1632, Delft, d. 1675, Delft)","title":"The Art of Painting (detail)","date":"1665-67","technique":"Oil on canvas","location":"Kunsthistorisches Museum, Vienna","url":"https://www.wga.hu/html/v/vermeer/03c/25artpa3.html","form":"painting","type":"mythological","school":"Dutch","timeline":"1651-1700"},{"author":"VERMEER, Johannes","born-died":"(b. 1632, Delft, d. 1675, Delft)","title":"The Art of Painting (detail)","date":"1665-67","technique":"Oil on canvas","location":"Kunsthistorisches Museum, Vienna","url":"https://www.wga.hu/html/v/vermeer/03c/25artpa4.html","form":"painting","type":"mythological","school":"Dutch","timeline":"1651-1700"},{"author":"VERMEER, Johannes","born-died":"(b. 1632, Delft, d. 1675, Delft)","title":"The Art of Painting (detail)","date":"1665-67","technique":"Oil on canvas","location":"Kunsthistorisches Museum, Vienna","url":"https://www.wga.hu/html/v/vermeer/03c/25artpa5.html","form":"painting","type":"mythological","school":"Dutch","timeline":"1651-1700"},{"author":"VERMEER, Johannes","born-died":"(b. 1632, Delft, d. 1675, Delft)","title":"The Allegory of the Catholic Faith","date":"1671-74","technique":"Oil on canvas, 114 x 89 cm","location":"Metropolitan Museum of Art, New York","url":"https://www.wga.hu/html/v/vermeer/04/33faith.html","form":"painting","type":"mythological","school":"Dutch","timeline":"1651-1700"},{"author":"VERMEER, Johannes","born-died":"(b. 1632, Delft, d. 1675, Delft)","title":"The Allegory of the Catholic Faith","date":"1671-74","technique":"Oil on canvas, 114 x 89 cm","location":"Metropolitan Museum of Art, New York","url":"https://www.wga.hu/html/v/vermeer/04/33faith0.html","form":"painting","type":"mythological","school":"Dutch","timeline":"1651-1700"},{"author":"VERMEER, Johannes","born-died":"(b. 1632, Delft, d. 1675, Delft)","title":"The Allegory of Catholic Faith (detail)","date":"1671-74","technique":"Oil on canvas","location":"Metropolitan Museum of Art, New York","url":"https://www.wga.hu/html/v/vermeer/04/33faith1.html","form":"painting","type":"mythological","school":"Dutch","timeline":"1651-1700"},{"author":"VERMEER, Johannes","born-died":"(b. 1632, Delft, d. 1675, Delft)","title":"The Allegory of Faith (detail)","date":"1671-74","technique":"Oil on canvas","location":"Metropolitan Museum of Art, New York","url":"https://www.wga.hu/html/v/vermeer/04/33faith2.html","form":"painting","type":"mythological","school":"Dutch","timeline":"1651-1700"},{"author":"VERMEER, Johannes","born-died":"(b. 1632, Delft, d. 1675, Delft)","title":"The Allegory of Catholic Faith (detail)","date":"1671-74","technique":"Oil on canvas","location":"Metropolitan Museum of Art, New York","url":"https://www.wga.hu/html/v/vermeer/04/33faith3.html","form":"painting","type":"mythological","school":"Dutch","timeline":"1651-1700"},{"author":"WERFF, Adriaen van der","born-died":"(b. 1659, Kralingen, d. 1722, Rotterdam)","title":"Amorous Shepherds","date":"c. 1690","technique":"Oil on canvas, 46 x 38 cm","location":"Staatliche Museen, Berlin","url":"https://www.wga.hu/html/w/werff/adriaen/amorous.html","form":"painting","type":"mythological","school":"Dutch","timeline":"1651-1700"},{"author":"WERFF, Adriaen van der","born-died":"(b. 1659, Kralingen, d. 1722, Rotterdam)","title":"Flora with Putti Strewing Flowers","date":1696,"technique":"Oil on canvas, 290 x 195 cm","location":"Staatliche Museen, Kassel","url":"https://www.wga.hu/html/w/werff/adriaen/flora.html","form":"painting","type":"mythological","school":"Dutch","timeline":"1651-1700"},{"author":"WERFF, Adriaen van der","born-died":"(b. 1659, Kralingen, d. 1722, Rotterdam)","title":"Flora with Putti Strewing Flowers (detail)","date":1696,"technique":"Oil on canvas","location":"Staatliche Museen, Kassel","url":"https://www.wga.hu/html/w/werff/adriaen/flora1.html","form":"painting","type":"mythological","school":"Dutch","timeline":"1651-1700"},{"author":"WERFF, Adriaen van der","born-died":"(b. 1659, Kralingen, d. 1722, Rotterdam)","title":"Lot and his Daughters","date":1711,"technique":"Oil on panel, 45 x 35 cm","location":"The Hermitage, St. Petersburg","url":"https://www.wga.hu/html/w/werff/adriaen/lot_daug.html","form":"painting","type":"mythological","school":"Dutch","timeline":"1651-1700"},{"author":"WERFF, Adriaen van der","born-died":"(b. 1659, Kralingen, d. 1722, Rotterdam)","title":"Flute Playing Shepherd","date":"c. 1696","technique":"Oil on canvas, 77 x 60 cm","location":"Private collection","url":"https://www.wga.hu/html/w/werff/adriaen/shephere.html","form":"painting","type":"mythological","school":"Dutch","timeline":"1651-1700"},{"author":"WERFF, Pieter van der","born-died":"(b. 1665, Kralingen, d. 1722, Rotterdam)","title":"Granida and Diafilo","date":1711,"technique":"Oil on panel 37 x 29 cm","location":"Wallraf-Richartz-Museum, Cologne","url":"https://www.wga.hu/html/w/werff/pieter/granida.html","form":"painting","type":"mythological","school":"Dutch","timeline":"1651-1700"},{"author":"WIJNEN, Domenicus van","born-died":"(b. 1661, Amsterdam, d. 1698, Amsterdam)","title":"Nurture of Bacchus","date":"-","technique":"Oil on canvas, 46 x 55 cm","location":"Musée des Beaux-Arts, Carcassonne","url":"https://www.wga.hu/html/w/wijnen/nurture.html","form":"painting","type":"mythological","school":"Dutch","timeline":"1651-1700"}]