[{"author":"MINIATURIST, German","born-died":"(active around 1300 in Upper Rhine)","title":"World Chronicle Charlemagne","date":"c. 1300","technique":"Manuscript (Ms. 302 Vad.), 305 x 210 mm","location":"Kantonsbinliothek Vadiana, St. Gall","url":"https://www.wga.hu/html/zgothic/miniatur/1301-350/4other/01_1301.html","form":"illumination","type":"historical","school":"German","timeline":"1301-1350"},{"author":"MINIATURIST, German","born-died":"(active around 1300 in Upper Rhine)","title":"World Chronicle Charlemagne","date":"c. 1300","technique":"Manuscript (Ms. 302 Vad.), 305 x 210 mm","location":"Kantonsbinliothek Vadiana, St. Gall","url":"https://www.wga.hu/html/zgothic/miniatur/1301-350/4other/02_1301.html","form":"illumination","type":"historical","school":"German","timeline":"1301-1350"},{"author":"MINIATURIST, German","born-died":"(active around 1310 in Alsace-Breisgau)","title":"World Chronicle Charlemagne","date":"c. 1310","technique":"Manuscript (Ms. germ. 623), 275 x 175 mm","location":"Staatsbibliothek, Berlin","url":"https://www.wga.hu/html/zgothic/miniatur/1301-350/4other/03_1301.html","form":"illumination","type":"historical","school":"German","timeline":"1301-1350"},{"author":"MINIATURIST, German","born-died":"(active around 1310 in Alsace-Breisgau)","title":"World Chronicle Charlemagne","date":"c. 1310","technique":"Manuscript (Ms. germ. 623), 275 x 175 mm","location":"Staatsbibliothek, Berlin","url":"https://www.wga.hu/html/zgothic/miniatur/1301-350/4other/04_1301.html","form":"illumination","type":"historical","school":"German","timeline":"1301-1350"},{"author":"MINIATURIST, German","born-died":"(active 14th century)","title":"Rudolf von Ems, Weltchronik","date":"14th century","technique":"Manuscript (MS Rh. 15)","location":"Zentralbibliothek, Zurich","url":"https://www.wga.hu/html/zgothic/miniatur/1301-350/4other/23_1301.html","form":"illumination","type":"historical","school":"German","timeline":"1301-1350"}]