[{"author":"ARCHITECT, German","born-died":"(active 13th century in Cologne)","title":"Interior view","date":"begun 1248","technique":"Photo","location":"Cathedral, Cologne","url":"https://www.wga.hu/html/zzzarchi/13c/1/20g_1258.html","form":"architecture","type":"other","school":"German","timeline":"1251-1300"},{"author":"ARCHITECT, German","born-died":"(active 13th century in Cologne)","title":"Interior view","date":"begun 1248","technique":"Photo","location":"Cathedral, Cologne","url":"https://www.wga.hu/html/zzzarchi/13c/1/20g_1259.html","form":"architecture","type":"other","school":"German","timeline":"1251-1300"},{"author":"ARCHITECT, German","born-died":"(active after 1277-1351 in Schleswig-Holstein)","title":"Exterior view","date":"1277-1351","technique":"Photo","location":"Marienkirche, Lübeck","url":"https://www.wga.hu/html/zzzarchi/13c/1/21g_1252.html","form":"architecture","type":"other","school":"German","timeline":"1251-1300"},{"author":"ARCHITECT, German","born-died":"(active 1250-1275 in Bavaria)","title":"Baumburg Tower","date":"1250-75","technique":"Photo","location":"Regensburg","url":"https://www.wga.hu/html/zzzarchi/13c/1/31g_1251.html","form":"architecture","type":"other","school":"German","timeline":"1251-1300"},{"author":"STEINBACH, Erwin von","born-died":"(b. ca. 1244, d. 1318, Strasbourg)","title":"Exterior view","date":"c. 1277","technique":"Photo","location":"Notre-Dame Cathedral, Strasbourg","url":"https://www.wga.hu/html/s/steinbac/strasbour.html","form":"architecture","type":"other","school":"German","timeline":"1251-1300"}]