[{"author":"MEDIEVAL SCULPTOR, French","born-died":"(active 1150-1200 at Chauvigny)","title":"Capital","date":"1150-1200","technique":"Stone","location":"Church of Sainte-Pierre, Chauvigny","url":"https://www.wga.hu/html/zgothic/1romanes/cap-12c3/05f_1168.html","form":"sculpture","type":"other","school":"French","timeline":"1151-1200"},{"author":"MEDIEVAL SCULPTOR, French","born-died":"(active 12th century)","title":"Figural capital","date":"12th century","technique":"Stone","location":"Priory church, Anzy-le-Duc (Brionnais)","url":"https://www.wga.hu/html/zgothic/1romanes/cap-12c3/13f_1168.html","form":"sculpture","type":"other","school":"French","timeline":"1151-1200"},{"author":"MEDIEVAL SCULPTOR, French","born-died":"(active 1160s)","title":"Tympanum and door lintel of the west portal (detail)","date":"1160s","technique":"Stone","location":"Church of Saint-Hilaire, Semur-en-Brionnais","url":"https://www.wga.hu/html/zgothic/1romanes/po-12c3/1f1_1168.html","form":"sculpture","type":"other","school":"French","timeline":"1151-1200"},{"author":"MEDIEVAL SCULPTOR, French","born-died":"(active 1170 in Senlis)","title":"West portal","date":"c. 1170","technique":"Stone","location":"Cathedral of Notre-Dame, Senlis (Oise)","url":"https://www.wga.hu/html/zgothic/1romanes/po-12c3/1f4_1167.html","form":"sculpture","type":"other","school":"French","timeline":"1151-1200"},{"author":"MEDIEVAL SCULPTOR, French","born-died":"(active around 1200 in Picardy)","title":"Central portal","date":"c. 1200","technique":"Stone","location":"Cathedral of Notre-Dame, Laon (Aisne)","url":"https://www.wga.hu/html/zgothic/1romanes/po-12c3/1f5_1167.html","form":"sculpture","type":"other","school":"French","timeline":"1151-1200"},{"author":"MEDIEVAL SCULPTOR, French","born-died":"(active around 1200 in Picardy)","title":"Central portal (detail)","date":"c. 1200","technique":"Stone","location":"Cathedral of Notre-Dame, Laon (Aisne)","url":"https://www.wga.hu/html/zgothic/1romanes/po-12c3/1f5_1168.html","form":"sculpture","type":"other","school":"French","timeline":"1151-1200"},{"author":"MEDIEVAL SCULPTOR, French","born-died":"(active around 1200 in Burgundy)","title":"West portal (detail)","date":"c. 1200","technique":"Stone","location":"Cathedral, Sens (Yonne)","url":"https://www.wga.hu/html/zgothic/1romanes/po-12c3/1f6_1167.html","form":"sculpture","type":"other","school":"French","timeline":"1151-1200"},{"author":"MEDIEVAL SCULPTOR, French","born-died":"(active 12th century in Pyrénées-Orientales)","title":"Tombstone","date":"12th century","technique":"Stone","location":"Cathedral of Sainte-Eulalie, Elne (Pyrénées-Orientales)","url":"https://www.wga.hu/html/zgothic/1romanes/re-1/5f1_1101.html","form":"sculpture","type":"other","school":"French","timeline":"1151-1200"},{"author":"MEDIEVAL SCULPTOR, French","born-died":"(active 1200-1225 in Anjou)","title":"Tomb of Richard the Lionheart and his Wife","date":"1200-25","technique":"Stone","location":"Abbey church, Fontevrault (Maine-et-Loire)","url":"https://www.wga.hu/html/zgothic/1romanes/re-1/5f2_1201.html","form":"sculpture","type":"other","school":"French","timeline":"1151-1200"}]