[{"author":"UNKNOWN GOLDSMITH, Flemish","born-died":"(active c. 1400 in South Netherlands)","title":"Acquamanile","date":"c. 1400","technique":"Bronze, height 33 cm","location":"Metropolitan Museum of Art, New York","url":"https://www.wga.hu/html/zzdeco/1gold/15c/08f_1400.html","form":"metalwork","type":"other","school":"Flemish","timeline":"1401-1450"},{"author":"UNKNOWN GOLDSMITH, Flemish","born-died":"(active mid-15th century in Burgundy)","title":"Beaker","date":"c. 1450","technique":"Rock crystal, gold, diamonds, rubies and pearls","location":"Private collection","url":"https://www.wga.hu/html/zzdeco/1gold/15c/08f_1450.html","form":"metalwork","type":"other","school":"Flemish","timeline":"1401-1450"}]